cdhf/__init__.py
cdhf/channel.py
cdhf/channel_member.py
cdhf/channel_member_history_entry.py
cdhf/data.py
cdhf/team.py
cdhf/team_member.py
cdhf/user_data.py
cdhf-1.1.dist-info/LICENSE
cdhf-1.1.dist-info/METADATA
cdhf-1.1.dist-info/WHEEL
cdhf-1.1.dist-info/top_level.txt
cdhf-1.1.dist-info/RECORD
