Metadata-Version: 2.1
Name: cdhf
Version: 1.1
Summary: CERN Data Handling Framework is a small framework to work with the CERN Anonymized Mattermost Data set
Home-page: https://github.com/mpobaschnig/cdhf
Author: Martin Pobaschnig
Author-email: mpobaschnig@protonmail.com
Project-URL: Bug Tracker, https://github.com/mpobaschnig/cdhf/issues
Classifier: Programming Language :: Python :: 3
Classifier: License :: OSI Approved :: GNU Lesser General Public License v3 (LGPLv3)
Classifier: Operating System :: OS Independent
Classifier: Topic :: Utilities
Requires-Python: >=3.6
License-File: LICENSE
